Metadata-Version: 1.1
Name: narmaw-profile
Version: 0.0.1
Summary: Narmaw Profile by NarMaw The Series
Home-page: https://github.com/nekokong/narmaw_profile
Author: Mumu Neko
Author-email: mumuneko.pk@gmail.com
License: MIT
Download-URL: https://github.com/nekokong/narmaw_profile/archive/v0.0.1.zip
Keywords: OOP,Profile,Mumu Neko
Platform: UNKNOWN
Classifier: Development Status :: 3 - Alpha
Classifier: Intended Audience :: Education
Classifier: Topic :: Utilities
Classifier: License :: OSI Approved :: MIT License
Classifier: Programming Language :: Python :: 3
Classifier: Programming Language :: Python :: 3.4
Classifier: Programming Language :: Python :: 3.5
Classifier: Programming Language :: Python :: 3.6
Classifier: Programming Language :: Python :: 3.7
Classifier: Programming Language :: Python :: 3.8
Classifier: Programming Language :: Python :: 3.9
Classifier: Programming Language :: Python :: 3.10
